uc_sso/__init__.py
uc_sso/main.py
uc_sso/parsers.py
uc_sso-1.0.3.dist-info/LICENSE
uc_sso-1.0.3.dist-info/WHEEL
uc_sso-1.0.3.dist-info/METADATA
uc_sso-1.0.3.dist-info/RECORD
