Metadata-Version: 2.1
Name: uc-sso
Version: 1.0.3
Summary: A helper for interacting locally with services that are protected by UC Chile's SSO.
Home-page: https://github.com/agucova/sso-uc
License:  AGPL-3.0-or-late
Keywords: uc-chile,uc,sso
Author: Agustín Covarrubias
Author-email: agucova@uc.cl
Requires-Python: >=3.9,<4.0
Classifier: License :: Other/Proprietary License
Classifier: Programming Language :: Python :: 3
Classifier: Programming Language :: Python :: 3.10
Classifier: Programming Language :: Python :: 3.9
Requires-Dist: html-table-parser-python3 (>=0.2.0,<0.3.0)
Requires-Dist: requests (>=2.27.1,<3.0.0)
Project-URL: Repository, https://github.com/agucova/sso-uc/
